pmatcher/__init__.py
pmatcher/pmatcher.py
pmatcher/test_pmatcher.py
pmatcher-0.1.14.dist-info/WHEEL
pmatcher-0.1.14.dist-info/METADATA
pmatcher-0.1.14.dist-info/RECORD
