Metadata-Version: 2.1
Name: pmatcher
Version: 0.1.14
Summary: Monadic election precinct matcher for gerrymandering data collection and research at MGGG
License: MIT
Author: Max Fan
Author-email: theinnovativeinventor@gmail.com
Requires-Python: >=3.7,<4.0
Classifier: License :: OSI Approved :: MIT License
Classifier: Programming Language :: Python :: 3
Classifier: Programming Language :: Python :: 3.7
Classifier: Programming Language :: Python :: 3.8
Classifier: Programming Language :: Python :: 3.9
Requires-Dist: fuzzywuzzy (>=0.18.0,<0.19.0)
Requires-Dist: python-Levenshtein (>=0.12.2,<0.13.0)
